pypi_test/__init__.py
pypi_test/main.py
pypi_test_demo-0.1.0.dist-info/METADATA
pypi_test_demo-0.1.0.dist-info/WHEEL
pypi_test_demo-0.1.0.dist-info/top_level.txt
pypi_test_demo-0.1.0.dist-info/RECORD
