Metadata-Version: 2.1
Name: pypi_test_demo
Version: 0.1.0
Summary: This is a sample package
Author: Muhammad Umer farooq
Author-email: umerfarooq397@gmail.com
Classifier: Programming Language :: Python :: 3
Classifier: License :: OSI Approved :: MIT License
Classifier: Operating System :: OS Independent
Requires-Python: >=3.6
